DhapLu_STT/__init__.py
dhaplu_stt-0.1.dist-info/METADATA
dhaplu_stt-0.1.dist-info/WHEEL
dhaplu_stt-0.1.dist-info/top_level.txt
dhaplu_stt-0.1.dist-info/RECORD
